ncoreparser/__init__.py
ncoreparser/client.py
ncoreparser/client_async.py
ncoreparser/data.py
ncoreparser/error.py
ncoreparser/parser.py
ncoreparser/torrent.py
ncoreparser/types.py
ncoreparser/util.py
ncoreparser-4.5.3.dist-info/WHEEL
ncoreparser-4.5.3.dist-info/METADATA
ncoreparser-4.5.3.dist-info/RECORD
