Metadata-Version: 2.4
Name: ncoreparser
Version: 4.5.3
Summary: Package to download from ncore.pro
Author: Aron Radics
Author-email: Aron Radics <aron.radics.jozsef@gmail.com>
License-Expression: MIT
Requires-Dist: httpx>=0.26.0
Requires-Python: >=3.9
Project-URL: Repository, https://github.com/radaron/ncoreparser.git
